[
    [
        "a",
        {"href":"/post/{id}"},
        [
            [
                "section",
                {
                    "id":"post{id}"
                },
                [
                    [
                        "div",
                        {"class":"infos"},
                        [
                            [
                                "span",
                                {"class":"author"},
                                "{author}"
                            ],
                            [
                                "span",
                                {"class":"date"},
                                "{date}"
                            ],
                            [
                                "span",
                                {"class":"category"},
                                "{category}"
                            ],
                            [
                                "span",
                                {"class":"info"},
                                "{tracks_nb} {tracks_nb_title}"
                            ]
                        ]
                    ],
                    [
                        "h2",
                        {"class":"title-small"},
                        "{title}"
                    ],
                    [
                        "div",
                        {"class":"excerpt"},
                        "{excerpt}"
                    ]
                ]
            ]
        ]
    ]
]